README.md
setup.py
flowdata/__init__.py
flowdata/_io.py
flowdata/_logger.py
flowdata/data_flow.py
flowdata/data_parallel.py
flowdata/decorator.py
flowdata/task.py
flowdata.egg-info/PKG-INFO
flowdata.egg-info/SOURCES.txt
flowdata.egg-info/dependency_links.txt
flowdata.egg-info/requires.txt
flowdata.egg-info/top_level.txt
test/__init__.py
test/test_dataParallel.py
test/test_flow.py
test/test_gputask.py
test/test_multitask.py