Metadata-Version: 2.1
Name: flowdata
Version: 0.1.6
Summary: 流式数据简易处理包
Home-page: https://github.com/zouweidong91/flowdata
Author: zouweidong
Author-email: zouweidong72@gmail.com
Requires-Python: >=3.6
